inky_pi/__init__.py
inky_pi/__main__.py
inky_pi/cli.py
inky_pi/configs.py
inky_pi/display/__init__.py
inky_pi/display/display_base.py
inky_pi/display/inky_draw.py
inky_pi/display/terminal_draw.py
inky_pi/display/util/__init__.py
inky_pi/display/util/desktop_driver.py
inky_pi/display/util/drawing.py
inky_pi/display/util/shapes.py
inky_pi/train/__init__.py
inky_pi/train/huxley2.py
inky_pi/train/open_live.py
inky_pi/train/train_base.py
inky_pi/util.py
inky_pi/weather/__init__.py
inky_pi/weather/open_weather_map.py
inky_pi/weather/weather_base.py
inky_pi-0.1.2.dist-info/LICENSE
inky_pi-0.1.2.dist-info/METADATA
inky_pi-0.1.2.dist-info/WHEEL
inky_pi-0.1.2.dist-info/entry_points.txt
inky_pi-0.1.2.dist-info/RECORD
