Metadata-Version: 2.1
Name: inky-pi
Version: 0.1.2
Summary: Top-level package for inky-pi.
Home-page: https://github.com/mickeykkim/inky_pi
License: MIT
Author: Mickey Kim
Author-email: mickeykkim@gmail.com
Requires-Python: >=3.8,<4
Classifier: Development Status :: 2 - Pre-Alpha
Classifier: Intended Audience :: Developers
Classifier: License :: OSI Approved :: MIT License
Classifier: Natural Language :: English
Classifier: Programming Language :: Python :: 3
Classifier: Programming Language :: Python :: 3.8
Classifier: Programming Language :: Python :: 3.9
Classifier: Programming Language :: Python :: 3.10
Classifier: Programming Language :: Python :: 3.11
Classifier: Programming Language :: Python :: 3.10
Classifier: Programming Language :: Python :: 3.11
Classifier: Programming Language :: Python :: 3.8
Classifier: Programming Language :: Python :: 3.9
Requires-Dist: Pillow (>=9.3.0,<10.0.0)
Requires-Dist: RPi.GPIO (>=0.7.0,<0.8.0) ; platform_machine == "armv7l"
Requires-Dist: click (>=8.1.2,<9.0.0)
Requires-Dist: environs (>=9.3.2,<10.0.0)
Requires-Dist: font-fredoka-one (>=0.0.4,<0.0.5)
Requires-Dist: font-hanken-grotesk (>=0.0.2,<0.0.3)
Requires-Dist: inky (>=1.2.0,<2.0.0) ; platform_machine == "armv7l"
Requires-Dist: loguru (>=0.6.0,<0.7.0)
Requires-Dist: numpy (>=1.22,<1.23)
Requires-Dist: rich (>=13.3.2,<14.0.0)
Requires-Dist: urllib3 (>=1.26.15,<2.0.0)
Requires-Dist: zeep (>=4.2.1,<5.0.0)
